lightcurvelynx/__init__.py
lightcurvelynx/_version.py
lightcurvelynx/base_models.py
lightcurvelynx/consts.py
lightcurvelynx/graph_state.py
lightcurvelynx/simulate.py
lightcurvelynx/astro_utils/__init__.py
lightcurvelynx/astro_utils/agn_utils.py
lightcurvelynx/astro_utils/black_body.py
lightcurvelynx/astro_utils/coordinate_utils.py
lightcurvelynx/astro_utils/detector_footprint.py
lightcurvelynx/astro_utils/dustmap.py
lightcurvelynx/astro_utils/mag_flux.py
lightcurvelynx/astro_utils/noise_model.py
lightcurvelynx/astro_utils/obs_utils.py
lightcurvelynx/astro_utils/passbands.py
lightcurvelynx/astro_utils/pzflow_node.py
lightcurvelynx/astro_utils/redshift.py
lightcurvelynx/astro_utils/salt2_color_law.py
lightcurvelynx/astro_utils/sed_basis_models.py
lightcurvelynx/astro_utils/snia_utils.py
lightcurvelynx/astro_utils/unit_utils.py
lightcurvelynx/astro_utils/zeropoint.py
lightcurvelynx/effects/__init__.py
lightcurvelynx/effects/basic_effects.py
lightcurvelynx/effects/effect_model.py
lightcurvelynx/effects/extinction.py
lightcurvelynx/effects/microlensing.py
lightcurvelynx/effects/white_noise.py
lightcurvelynx/example_runs/simulate_snia.py
lightcurvelynx/math_nodes/__init__.py
lightcurvelynx/math_nodes/basic_math_node.py
lightcurvelynx/math_nodes/bilby_priors.py
lightcurvelynx/math_nodes/distribution_sampler.py
lightcurvelynx/math_nodes/given_sampler.py
lightcurvelynx/math_nodes/np_random.py
lightcurvelynx/math_nodes/ra_dec_sampler.py
lightcurvelynx/math_nodes/scipy_random.py
lightcurvelynx/math_nodes/single_value_node.py
lightcurvelynx/models/__init__.py
lightcurvelynx/models/agn.py
lightcurvelynx/models/bagle_models.py
lightcurvelynx/models/basic_models.py
lightcurvelynx/models/bayesn.py
lightcurvelynx/models/galaxy_models.py
lightcurvelynx/models/lightcurve_template_model.py
lightcurvelynx/models/multi_object_model.py
lightcurvelynx/models/periodic_model.py
lightcurvelynx/models/periodic_variable_star.py
lightcurvelynx/models/physical_model.py
lightcurvelynx-0.2.5.dist-info/licenses/LICENSE
lightcurvelynx-0.2.5.dist-info/METADATA
lightcurvelynx-0.2.5.dist-info/WHEEL
lightcurvelynx-0.2.5.dist-info/top_level.txt
lightcurvelynx-0.2.5.dist-info/RECORD
