Metadata-Version: 2.4
Name: lightcurvelynx
Version: 0.2.5
Author-email: LINCC Frameworks <lincc-frameworks-team@lists.lsst.org>
License-Expression: MIT
Project-URL: Source Code, https://github.com/lincc-frameworks/lightcurvelynx
Classifier: Development Status :: 4 - Beta
Classifier: Intended Audience :: Developers
Classifier: Intended Audience :: Science/Research
Classifier: Operating System :: OS Independent
Classifier: Programming Language :: Python
Requires-Python: >=3.10
License-File: LICENSE
Requires-Dist: astropy
Requires-Dist: cdshealpix
Requires-Dist: citation-compass>=0.0.3
Requires-Dist: matplotlib
Requires-Dist: mocpy
Requires-Dist: nested-pandas
Requires-Dist: networkx
Requires-Dist: numpy>=2.0
Requires-Dist: pandas
Requires-Dist: pooch
Requires-Dist: PyYAML>=6.0
Requires-Dist: regions
Requires-Dist: scipy
Requires-Dist: tqdm
Provides-Extra: dev
Requires-Dist: asv[virtualenv]==0.6.5; extra == "dev"
Requires-Dist: bilby; extra == "dev"
Requires-Dist: dust_extinction; extra == "dev"
Requires-Dist: extinction>=0.4.7; extra == "dev"
Requires-Dist: fsspec[http]; extra == "dev"
Requires-Dist: jupyter; extra == "dev"
Requires-Dist: jax; extra == "dev"
Requires-Dist: lsdb; extra == "dev"
Requires-Dist: networkx; extra == "dev"
Requires-Dist: pre-commit; extra == "dev"
Requires-Dist: pytest; extra == "dev"
Requires-Dist: pytest-cov; extra == "dev"
Requires-Dist: pzflow; extra == "dev"
Requires-Dist: ruff; extra == "dev"
Requires-Dist: sncosmo; extra == "dev"
Requires-Dist: synphot; extra == "dev"
Requires-Dist: VBMicrolensing; extra == "dev"
Provides-Extra: all
Requires-Dist: bilby; extra == "all"
Requires-Dist: dust_extinction; extra == "all"
Requires-Dist: extinction>=0.4.7; extra == "all"
Requires-Dist: jax; extra == "all"
Requires-Dist: lsdb; extra == "all"
Requires-Dist: networkx; extra == "all"
Requires-Dist: pzflow; extra == "all"
Requires-Dist: sncosmo; extra == "all"
Requires-Dist: synphot; extra == "all"
Requires-Dist: VBMicrolensing; extra == "all"
Dynamic: license-file
